dynetworkx/__init__.py
dynetworkx/algorithms/__init__.py
dynetworkx/algorithms/count_temporal_motif.py
dynetworkx/classes/__init__.py
dynetworkx/classes/impulsedigraph.py
dynetworkx/classes/impulsegraph.py
dynetworkx/classes/intervaldigraph.py
dynetworkx/classes/intervalgraph.py
dynetworkx/classes/intervaltree.py
dynetworkx/classes/snapshotdigraph.py
dynetworkx/classes/snapshotgraph.py
dynetworkx/tests/__init__.py
dynetworkx/tests/test_count_temporal_motif.py
dynetworkx/tests/test_impulsedigraph.py
dynetworkx/tests/test_impulsegraph.py
dynetworkx/tests/test_intervaldigraph.py
dynetworkx/tests/test_intervalgraph.py
dynetworkx/tests/test_snapshotgraph.py
DyNetworkX-4.0.dist-info/LICENSE.txt
DyNetworkX-4.0.dist-info/METADATA
DyNetworkX-4.0.dist-info/WHEEL
DyNetworkX-4.0.dist-info/top_level.txt
DyNetworkX-4.0.dist-info/RECORD
