Metadata-Version: 2.1
Name: DyNetworkX
Version: 4.0
Summary: DyNetworkX is a Python package for the study of dynamic network analysis.
Home-page: https://github.com/IdeasLabUT/dynetworkx
Author: Makan Arastuie
Author-email: Makan.Arastuie@rockets.utoledo.edu
License: Released under the 3-Clause BSD license.
Platform: UNKNOWN
Requires-Python: >=3.4
License-File: LICENSE.txt
Requires-Dist: networkx
Requires-Dist: sortedcontainers
Requires-Dist: numpy
Requires-Dist: timeit
Requires-Dist: sklearn
